pyalink/LICENSE
pyalink/__init__.py
pyalink/alink/__init__.py
pyalink/alink/config.py
pyalink/alink/download_pyalink_dep_jars.py
pyalink/alink/env.py
pyalink/alink/ipython_magic_command.py
pyalink/alink/plugin_downloader.py
pyalink/alink/py4j_util.py
pyalink/alink/version.py
pyalink/alink/batch/__init__.py
pyalink/alink/batch/base.py
pyalink/alink/batch/lazy_evaluation.py
pyalink/alink/batch/mixins.py
pyalink/alink/batch/operator_with_methods.py
pyalink/alink/batch/special_operators.py
pyalink/alink/batch/common/__init__.py
pyalink/alink/batch/common/batch_op_1.py
pyalink/alink/batch/common/batch_op_10.py
pyalink/alink/batch/common/batch_op_11.py
pyalink/alink/batch/common/batch_op_2.py
pyalink/alink/batch/common/batch_op_3.py
pyalink/alink/batch/common/batch_op_4.py
pyalink/alink/batch/common/batch_op_5.py
pyalink/alink/batch/common/batch_op_6.py
pyalink/alink/batch/common/batch_op_7.py
pyalink/alink/batch/common/batch_op_8.py
pyalink/alink/batch/common/batch_op_9.py
pyalink/alink/common/__init__.py
pyalink/alink/common/sql/__init__.py
pyalink/alink/common/sql/sql_query_utils.py
pyalink/alink/common/types/__init__.py
pyalink/alink/common/types/data_type_display.py
pyalink/alink/common/types/metrics.py
pyalink/alink/common/types/model_info.py
pyalink/alink/common/types/mtable.py
pyalink/alink/common/types/stat_summary.py
pyalink/alink/common/types/tensor.py
pyalink/alink/common/types/train_info.py
pyalink/alink/common/types/vector.py
pyalink/alink/common/types/bases/__init__.py
pyalink/alink/common/types/bases/algo_operator.py
pyalink/alink/common/types/bases/j_obj_wrapper.py
pyalink/alink/common/types/bases/model_stream_scan_params.py
pyalink/alink/common/types/bases/params.py
pyalink/alink/common/types/bases/with_params.py
pyalink/alink/common/types/catalog/__init__.py
pyalink/alink/common/types/catalog/catalog.py
pyalink/alink/common/types/catalog/catalog_object.py
pyalink/alink/common/types/conversion/__init__.py
pyalink_flink_1.12-1.6.2.post0.dist-info/METADATA
pyalink_flink_1.12-1.6.2.post0.dist-info/WHEEL
pyalink_flink_1.12-1.6.2.post0.dist-info/entry_points.txt
pyalink_flink_1.12-1.6.2.post0.dist-info/top_level.txt
pyalink_flink_1.12-1.6.2.post0.dist-info/RECORD
